pysqlcipher/__init__.py
pysqlcipher/_sqlite.so
pysqlcipher/dbapi2.py
pysqlcipher/dump.py
pysqlcipher/test/__init__.py
pysqlcipher/test/dbapi.py
pysqlcipher/test/dump.py
pysqlcipher/test/factory.py
pysqlcipher/test/hooks.py
pysqlcipher/test/regression.py
pysqlcipher/test/transactions.py
pysqlcipher/test/types.py
pysqlcipher/test/userfunctions.py
pysqlcipher/test/py25/__init__.py
pysqlcipher/test/py25/py25tests.py
pysqlcipher-2.6.4.dist-info/DESCRIPTION.rst
pysqlcipher-2.6.4.dist-info/METADATA
pysqlcipher-2.6.4.dist-info/metadata.json
pysqlcipher-2.6.4.dist-info/RECORD
pysqlcipher-2.6.4.dist-info/top_level.txt
pysqlcipher-2.6.4.dist-info/WHEEL
