Metadata-Version: 2.0
Name: pysqlcipher
Version: 2.6.4
Summary: DB-API 2.0 interface for SQLCIPHER 3.x
Home-page: http://github.com/leapcode/pysqlcipher/
Author: Kali Kaneko
Author-email: kali@leap.se
License: zlib/libpng
Platform: ALL
Classifier: Development Status :: 4 - Beta
Classifier: Intended Audience :: Developers
Classifier: License :: OSI Approved :: zlib/libpng License
Classifier: Operating System :: MacOS :: MacOS X
Classifier: Operating System :: Microsoft :: Windows
Classifier: Operating System :: POSIX
Classifier: Programming Language :: C
Classifier: Programming Language :: Python
Classifier: Topic :: Database :: Database Engines/Servers
Classifier: Topic :: Software Development :: Libraries :: Python Modules
